csv_log_module/__init__.py
csv_log_module/core.py
csv_log_module-1.0.0.dist-info/METADATA
csv_log_module-1.0.0.dist-info/WHEEL
csv_log_module-1.0.0.dist-info/RECORD
