Metadata-Version: 2.4
Name: csv-log-module
Version: 1.0.0
Summary: A simple CSV-based scoring log with beautiful rich terminal display
Author: Anton
Keywords: csv,logging,rich,scores
Classifier: Operating System :: OS Independent
Classifier: Programming Language :: Python :: 3
Requires-Python: >=3.8
Requires-Dist: pandas
Requires-Dist: rich
